pylint_unittest/__init__.py
pylint_unittest/__pkginfo__.py
pylint_unittest/checkers.py
pylint_unittest/utils.py
tests/__init__.py
tests/test_checkers.py
pylint_unittest-0.2.0.dist-info/LICENSE
pylint_unittest-0.2.0.dist-info/METADATA
pylint_unittest-0.2.0.dist-info/WHEEL
pylint_unittest-0.2.0.dist-info/top_level.txt
pylint_unittest-0.2.0.dist-info/RECORD
