Metadata-Version: 2.1
Name: pylint-unittest
Version: 0.2.0
Summary: A Pylint plugin for detecting incorrect use of unittest assertions
Home-page: https://github.com/federicobond/pylint-unittest
Author: Federico Bond
Author-email: federicobond@gmail.com
License: GPLv3
Keywords: pylint,unittest,plugin
Classifier: Development Status :: 3 - Alpha
Classifier: Environment :: Console
Classifier: Intended Audience :: Developers
Classifier: Operating System :: Unix
Classifier: Topic :: Software Development :: Quality Assurance
Classifier: Programming Language :: Python :: 3
Classifier: Programming Language :: Python :: 3.6
License-File: LICENSE
Requires-Dist: pylint
